ChangeLog
LICENSE
MANIFEST.in
README
setup.cfg
setup.py
examples/clusterrun.py
examples/fulton.py
examples/kjv10.txt
examples/make-gutindex.py
examples/wordcount.py
examples/wordcount2.py
examples/contrib/dependency_parse.py
examples/contrib/walk_analyzer/conditional_prob.py
examples/contrib/walk_analyzer/walk_analyzer.py
examples/contrib/walk_analyzer/hadoop_code/ConditionalProb.java
examples/contrib/walk_analyzer/hadoop_code/Pair.java
examples/contrib/walk_analyzer/hadoop_code/WalkAnalyzer.java
examples/contrib/walk_analyzer/hadoop_code/WalkFileInputFormat.java
examples/contrib/walk_analyzer/hadoop_code/WalkPath.java
examples/pi/Pi.java
examples/pi/c_pi.py
examples/pi/halton.c
examples/pi/pure_pi.py
mrs/__init__.py
mrs/bucket.py
mrs/computed_data.py
mrs/datasets.py
mrs/fileformats.py
mrs/hdfs.py
mrs/http.py
mrs/job.py
mrs/main.py
mrs/mapreduce.py
mrs/master.py
mrs/param.py
mrs/peons.py
mrs/registry.py
mrs/runner.py
mrs/serial.py
mrs/serializers.py
mrs/slave.py
mrs/tasks.py
mrs/util.py
mrs/version.py
mrs/worker.py
mrs_mapreduce.egg-info/PKG-INFO
mrs_mapreduce.egg-info/SOURCES.txt
mrs_mapreduce.egg-info/dependency_links.txt
mrs_mapreduce.egg-info/top_level.txt
tests/data/dickens/split1.txt
tests/data/dickens/split2.txt
tests/data/dickens/split3.txt
tests/data/dickens/split4.txt
tests/data/dickens/split5.txt
tests/data/dickens/split6.txt
tests/data/dickens/split7.txt
tests/data/dickens/split8.txt
tests/hdfs/test_hdfs.py
tests/integration/__init__.py
tests/integration/conftest.py
tests/integration/test_pso.py
tests/integration/test_wordcount.py
tests/integration/test_wordcount2.py
tests/integration/wordcount.py
tests/integration/wordcount2.py
tests/master/test_idle_slaves.py
tests/param/__init__.py
tests/param/conftest.py
tests/param/test_param.py