Metadata-Version: 1.1
Name: mrs-mapreduce
Version: 0.9
Summary: A lightweight MapReduce implementation for computationally intensive programs
Home-page: http://code.google.com/p/mrs-mapreduce/
Author: Andrew McNabb
Author-email: mrs-mapreduce@googlegroups.com
License: Apache License, Version 2.0
Platform: UNKNOWN
Classifier: Development Status :: 4 - Beta
Classifier: Operating System :: POSIX :: Linux
Classifier: Environment :: Console
Classifier: Intended Audience :: Science/Research
Classifier: License :: OSI Approved :: Apache Software License
Classifier: Natural Language :: English
Classifier: Programming Language :: Python
Classifier: Programming Language :: Python :: 2
Classifier: Programming Language :: Python :: 2.6
Classifier: Programming Language :: Python :: 2.7
Classifier: Programming Language :: Python :: 3
Classifier: Programming Language :: Python :: 3.1
Classifier: Programming Language :: Python :: 3.2
Classifier: Topic :: Scientific/Engineering :: Information Analysis
